control_unit/uc_asm.v
module uc_asm (
  input wire reset,
  input wire clk,
  output reg WE_RF,
  output reg WE_MEM,
  output reg[1:0] RF_din_sel,
  output reg ULA_din2_sel,
  output reg load_pc,
  output reg load_ir,
  output reg pc_next_sel,
  output reg pc_adder_sel
);

  parameter FETCH = 2'b00,
            DECODE = 2'b01,
            EXECUTE_ADDSUB = 2'b10,
            WRITE_BACK = 2'b11;

  reg[1:0] current_state, next_state;

  always @(posedge clk or posedge reset) begin
    if (reset) begin
      current_state <= FETCH;
    end
    else begin
      current_state <= next_state;
    end
  end

  always @(current_state) begin
    case (current_state)
      FETCH: begin
        next_state <= DECODE;
      end

      DECODE: begin
        next_state <= EXECUTE_ADDSUB;
      end

      EXECUTE_ADDSUB: begin
        next_state <= WRITE_BACK; 
      end

      default: begin
        next_state <= FETCH;
      end
    endcase
  end

    always @(current_state) begin
      case (current_state)
        FETCH: begin
          // PC = PC + 4
          // IR = INSTRUCTION_MEMORY[PC]
          pc_next_sel = 1'b0;
          load_ir = 1'b1;
          load_pc = 1'b1;
          WE_RF = 1'b0;
          WE_MEM = 1'b1;
          RF_din_sel = 1'b0;
          ULA_din2_sel = 1'b0;
        end 
        DECODE: begin
          load_ir = 1'b0;
          load_pc = 1'b0;
        end
        EXECUTE_ADDSUB: begin
          RF_din_sel = 2'b01;
          ULA_din2_sel = 1'b0;
        end
        WRITE_BACK: begin
          WE_RF = 1'b1;
        end
      endcase
    end
  
endmodule

control_unit/testbenches/uc_asm_tb.v
`include "control_unit/uc_asm.v"

module uc_asm_tb;
  
  wire WE_RF, WE_MEM, ULA_din2_sel, load_pc, load_ir, pc_next_sel, pc_adder_sel;
  wire[1:0] RF_din_sel;
  reg clk, reset;

  uc_asm UUT (
    .reset(reset),
    .clk(clk),
    .WE_RF(WE_RF),
    .WE_MEM(WE_MEM),
    .RF_din_sel(RF_din_sel),
    .ULA_din2_sel(ULA_din2_sel),
    .load_pc(load_pc),
    .load_ir(load_ir),
    .pc_next_sel(pc_next_sel),
    .pc_adder_sel(pc_adder_sel)
  );

  initial begin
    $dumpfile("control_unit/testbenches/waves/uc_asm/waveforms3.vcd");
    $dumpvars(0, uc_asm_tb);
    clk = 0;
    reset = 1;
    #10
    reset = 0;
    #100
    $finish;
  end

  always #5 clk = ~clk;

endmodule

control_unit/testbenches/waves/uc_asm/waveforms3.vcd
$date
	Mon May 29 21:40:14 2023
$end
$version
	Icarus Verilog
$end
$timescale
	1s
$end
$scope module uc_asm_tb $end
$var wire 1 ! pc_next_sel $end
$var wire 1 " pc_adder_sel $end
$var wire 1 # load_pc $end
$var wire 1 $ load_ir $end
$var wire 1 % WE_RF $end
$var wire 1 & WE_MEM $end
$var wire 1 ' ULA_din2_sel $end
$var wire 2 ( RF_din_sel [1:0] $end
$var reg 1 ) clk $end
$var reg 1 * reset $end
$scope module UUT $end
$var wire 1 ) clk $end
$var wire 1 * reset $end
$var parameter 2 + DECODE $end
$var parameter 2 , EXECUTE_ADDSUB $end
$var parameter 2 - FETCH $end
$var parameter 2 . WRITE_BACK $end
$var reg 2 / RF_din_sel [1:0] $end
$var reg 1 ' ULA_din2_sel $end
$var reg 1 & WE_MEM $end
$var reg 1 % WE_RF $end
$var reg 2 0 current_state [1:0] $end
$var reg 1 $ load_ir $end
$var reg 1 # load_pc $end
$var reg 2 1 next_state [1:0] $end
$var reg 1 " pc_adder_sel $end
$var reg 1 ! pc_next_sel $end
$upscope $end
$upscope $end
$enddefinitions $end
$comment Show the parameter values. $end
$dumpall
b11 .
b0 -
b10 ,
b1 +
$end
#0
$dumpvars
b1 1
b0 0
b0 /
1*
0)
b0 (
0'
1&
0%
1$
1#
x"
0!
$end
#5
1)
#10
0)
0*
#15
b10 1
0#
0$
b1 0
1)
#20
0)
#25
b11 1
b1 (
b1 /
b10 0
1)
#30
0)
#35
b0 1
1%
b11 0
1)
#40
0)
#45
b1 1
b0 (
b0 /
0%
1#
1$
b0 0
1)
#50
0)
#55
b10 1
0#
0$
b1 0
1)
#60
0)
#65
b11 1
b1 (
b1 /
b10 0
1)
#70
0)
#75
b0 1
1%
b11 0
1)
#80
0)
#85
b1 1
b0 (
b0 /
0%
1#
1$
b0 0
1)
#90
0)
#95
b10 1
0#
0$
b1 0
1)
#100
0)
#105
b11 1
b1 (
b1 /
b10 0
1)
